pynucamino/__init__.py
pynucamino/executable.py
pynucamino/functions.py
pynucamino/nucalign.py
pynucamino/nucamino.py
pynucamino/nucamino_executable.py
pynucamino/bin/nucamino-darwin-386
pynucamino/bin/nucamino-darwin-amd64
pynucamino/bin/nucamino-linux-386
pynucamino/bin/nucamino-linux-amd64
pynucamino/bin/nucamino-windows-386.exe
pynucamino/bin/nucamino-windows-amd64.exe
pynucamino-0.1.0.dist-info/METADATA
pynucamino-0.1.0.dist-info/RECORD
pynucamino-0.1.0.dist-info/WHEEL
pynucamino-0.1.0.dist-info/top_level.txt
test/__init__.py
test/test_executable.py
test/test_functions.py
test/test_integrated.py
test/test_nucamino.py
